notebook_utils/__init__.py
notebook_utils/collab.py
notebook_utils/version.py
notebook_utils/widgets.py
notebooks/__init__.py
tests/__init__.py
notebook_utils-0.2.0.dist-info/METADATA
notebook_utils-0.2.0.dist-info/WHEEL
notebook_utils-0.2.0.dist-info/top_level.txt
notebook_utils-0.2.0.dist-info/RECORD
