Metadata-Version: 2.1
Name: notebook-utils
Version: 0.2.0
Summary: Python jupyter notebook helper utilities
Author: Sam Bland
Author-email: sbland.co.uk@gmail.com
Classifier: Programming Language :: Python :: 3.7
Classifier: Operating System :: OS Independent
Requires-Dist: wheel
Requires-Dist: scipy
Requires-Dist: numpy
Requires-Dist: pandas
Requires-Dist: matplotlib
Requires-Dist: deprecated
Provides-Extra: test
Requires-Dist: pytest ; extra == 'test'
Requires-Dist: numpy ; extra == 'test'
Requires-Dist: pandas ; extra == 'test'
